CHANGES
LICENSE
MANIFEST.in
Makefile
README.rst
dev-requirements.txt
requirements.txt
runtests.py
setup.py
tox.ini
docs/Makefile
docs/conf.py
docs/index.rst
docs/intro.rst
docs/_ext/djangodocs.py
docs/_themes/kr/layout.html
docs/_themes/kr/relations.html
docs/_themes/kr/theme.conf
docs/_themes/kr/static/flasky.css_t
docs/_themes/kr/static/small_flask.css
epochdatetimefield/__init__.py
epochdatetimefield/fields.py
epochdatetimefield/models.py
epochdatetimefield.egg-info/PKG-INFO
epochdatetimefield.egg-info/SOURCES.txt
epochdatetimefield.egg-info/dependency_links.txt
epochdatetimefield.egg-info/not-zip-safe
epochdatetimefield.egg-info/requires.txt
epochdatetimefield.egg-info/top_level.txt
epochdatetimefield/tests/__init__.py
epochdatetimefield/tests/models.py
epochdatetimefield/tests/test_models.py