Metadata-Version: 1.0
Name: epochdatetimefield
Version: 0.0.1
Summary: 
